{
	"required": true,
	"minVersion": "0.8",
	"package": "net.grilledham.hamhacks.mixin",
	"compatibilityLevel": "JAVA_17",
	"client": [
		"MixinBlockEntityRenderDispatcher",
		"MixinBlockModelRenderer",
		"MixinCamera",
		"MixinChatHud",
		"MixinChunkOcclusionDataBuilder",
		"MixinClientConnection",
		"MixinClientPlayerEntity",
		"MixinClientPlayerInteractionManager",
		"MixinClientPlayNetworkHandler",
		"MixinCommandSuggestor",
		"MixinEntityRenderer",
		"MixinFluidRenderer",
		"MixinGameRenderer",
		"MixinHeldItemRenderer",
		"MixinInGameHud",
		"MixinInGameOverlayRenderer",
		"MixinIntegratedServer",
		"MixinKeyBinding",
		"MixinKeyboard",
		"MixinKeyboardInput",
		"MixinLanguageManager",
		"MixinLightmapTextureManager",
		"MixinMinecraftClient",
		"MixinMouse",
		"MixinMultiplayerScreen",
		"MixinRenderTickCounter",
		"MixinTelemetryManager",
		"MixinTextVisitFactory",
		"MixinTitleScreen"
	],
	"mixins": [
		"MixinAbstractBlockState",
		"MixinBoatEntity",
		"MixinEntityVelocityUpdateS2CPacket",
		"MixinMatrix4f",
		"MixinPlayerEntity",
		"MixinVec3d",
		"MixinYggdrasilUserApiService",
		"baritone.MixinComeCommand",
		"sodium.MixinBlockOcclusionCache",
		"sodium.MixinBlockRenderer",
		"sodium.MixinFluidRenderer"
	]
}
